{"data": [["January-February, 2024","ind","January-February, 2024","indA",0,"Family health history","Demographic Characteristics","",null,"86.6","84.5, 88.4","89.0","87.1, 90.6","87.8","86.1, 89.5","87.1","84.6, 89.3",""]], "classes": ["Year","row_var","rowLevels","rowLevNum","selected","stat_group","col_group","new_caption","new_caption2","Large central metro__metroA__Familyhealthhistory17__coef","Large central metro__metroA__Familyhealthhistory17__se","Large fringe metro__metroB__Familyhealthhistory17__coef","Large fringe metro__metroB__Familyhealthhistory17__se","Medium and small metro__metroC__Familyhealthhistory17__coef","Medium and small metro__metroC__Familyhealthhistory17__se","Nonmetropolitan__metroD__Familyhealthhistory17__coef","Nonmetropolitan__metroD__Familyhealthhistory17__se","subLevels"], "names": ["Year","row_var","rowLevels","rowLevNum","selected","stat_group","col_group","new_caption","new_caption2","Large central metro","Large central metro","Large fringe metro","Large fringe metro","Medium and small metro","Medium and small metro","Nonmetropolitan","Nonmetropolitan","subLevels"], "caption": ["Percentage of adults who know at least some of their biological father’s health history"], "caption2": [""], "caption3": [null]}
