{"data": [["January-February, 2024","ind","January-February, 2024","indA",0,"Sexual health","Socio-economic status","",null,"29.4","27.2, 31.8","31.2","29.1, 33.4","33.0","31.0, 35.1",""]], "classes": ["Year","row_var","rowLevels","rowLevNum","selected","stat_group","col_group","new_caption","new_caption2","High school degree or GED or less__EducationA__Sexualhealth74__coef","High school degree or GED or less__EducationA__Sexualhealth74__se","Some college__EducationB__Sexualhealth74__coef","Some college__EducationB__Sexualhealth74__se","Bachelors degree or higher__EducationC__Sexualhealth74__coef","Bachelors degree or higher__EducationC__Sexualhealth74__se","subLevels"], "names": ["Year","row_var","rowLevels","rowLevNum","selected","stat_group","col_group","new_caption","new_caption2","High school degree or GED or less","High school degree or GED or less","Some college","Some college","Bachelors degree or higher","Bachelors degree or higher","subLevels"], "caption": ["Percentage of adults who would turn to their peers or friends for information about sexual health "], "caption2": [""], "caption3": [null]}
