{"data": [["January-February, 2024","ind","January-February, 2024","indA",0,"Sexual health","Demographic Characteristics","",null,"15.3","13.4, 17.5","14.2","12.3, 16.4","15.0","13.2, 16.9","12.3","10.1, 14.8",""]], "classes": ["Year","row_var","rowLevels","rowLevNum","selected","stat_group","col_group","new_caption","new_caption2","Large central metro__metroA__Sexualhealth72__coef","Large central metro__metroA__Sexualhealth72__se","Large fringe metro__metroB__Sexualhealth72__coef","Large fringe metro__metroB__Sexualhealth72__se","Medium and small metro__metroC__Sexualhealth72__coef","Medium and small metro__metroC__Sexualhealth72__se","Nonmetropolitan__metroD__Sexualhealth72__coef","Nonmetropolitan__metroD__Sexualhealth72__se","subLevels"], "names": ["Year","row_var","rowLevels","rowLevNum","selected","stat_group","col_group","new_caption","new_caption2","Large central metro","Large central metro","Large fringe metro","Large fringe metro","Medium and small metro","Medium and small metro","Nonmetropolitan","Nonmetropolitan","subLevels"], "caption": ["Percentage of adults who would turn to their family for information about sexual health "], "caption2": [""], "caption3": [null]}
